{"ItemId":21050046,"IsShow":true,"WeaponName":"和光回唱","QualityId":5,"WeaponType":5,"ModelId":21050046,"TransformId":5,"Models":[21050046],"ModelsIndex":[0],"ResonLevelLimit":5,"FirstPropId":{"Id":7,"Value":40,"IsRatio":false},"FirstCurve":1,"SecondPropId":{"Id":8,"Value":800,"IsRatio":false},"SecondCurve":2,"ResonId":21050046,"LevelId":5,"BreachId":21050046,"StandAnim":["/Game/Aki/Character/Weapon/Device/R5Device504/CommonAnim/AC_UI_Open_Loop2.AC_UI_Open_Loop2"],"Desc":"攻击提升<span style=\"color:#ffd12f;\" class=\"font-bold\">12%/15%/18%/21%/24%</span>。对附加了【光噪效应】的目标造成伤害时，自身普攻、重击伤害加成提升<span style=\"color:#ffd12f;\" class=\"font-bold\">14%/17.5%/21%/24.5%/28%</span>，可以叠加<span style=\"color:#ffd12f;\" class=\"font-bold\">3/3/3/3/3</span>层，持续<span style=\"color:#ffd12f;\" class=\"font-bold\">6/6/6/6/6</span>秒。施放延奏技能时，使队伍中登场角色周围的目标受到【光噪效应】伤害加深<span style=\"color:#ffd12f;\" class=\"font-bold\">30%/37.5%/45%/52.5%/60%</span>，持续<span style=\"color:#ffd12f;\" class=\"font-bold\">30/30/30/30/30</span>秒，同名效果之间不可叠加。","DescParams":[{"ArrayString":["12%","15%","18%","21%","24%"]},{"ArrayString":["14%","17.5%","21%","24.5%","28%"]},{"ArrayString":["3","3","3","3","3"]},{"ArrayString":["6","6","6","6","6"]},{"ArrayString":["30%","37.5%","45%","52.5%","60%"]},{"ArrayString":["30","30","30","30","30"]}],"TypeDescription":"武器","AttributesDescription":"「岁主恩典，何等甘甜，家园今得寻见；衔枝踏浪，以爱相连，圣辉化作冠冕。」","BgDescription":"「岁主恩典，何等甘甜，家园今得寻见；衔枝踏浪，以爱相连，圣辉化作冠冕。」","Icon":"/Game/Aki/UI/UIResources/Common/Image/IconWeapon/T_IconWeapon21050029_UI.T_IconWeapon21050029_UI","IconMiddle":"/Game/Aki/UI/UIResources/Common/Image/IconWeapon160/T_IconWeapon160_21050029_UI.T_IconWeapon160_21050029_UI","IconSmall":"/Game/Aki/UI/UIResources/Common/Image/IconWeapon80/T_IconWeapon80_21050029_UI.T_IconWeapon80_21050029_UI","IconBig":"/Game/Aki/UI/UIResources/Common/Image/IconWeapon732/T_IconWeapon732_21050029_UI.T_IconWeapon732_21050029_UI","Mesh":"/Game/Aki/Scene/Assets/Common/Interaction/Mesh/SM_Pro_Roc_04ES.SM_Pro_Roc_04ES","MaxCapcity":999999999,"ItemAccess":[],"ObtainedShow":1,"ObtainedShowDescription":"「岁主恩典，何等甘甜，家园今得寻见；衔枝踏浪，以爱相连，圣辉化作冠冕。」","NumLimit":1,"ShowInBag":true,"SortIndex":0,"ResonanceIcon":"","HiddenTime":10,"Destructible":false,"RedDotDisableRule":0,"HandBookTrialId":5501103,"QualityName":"SSR","WeaponTypeName":"音感仪","TypeIcon":"/Game/Aki/UI/UIResources/Common/Atlas/SkillIcon/SkillIconNor/SP_IconNorMagic.SP_IconNorMagic","ResonName":"衔枝者赞诗","Breaches":[{"Id":849,"BreachId":21050046,"Level":0,"ConditionId":504002,"LevelLimit":20,"Consume":[{"Key":41100031,"Value":6}],"GoldConsume":10000,"Items":[{"Key":41100031,"Value":6,"Icon":"/Game/Aki/UI/UIResources/Common/Image/IconMout/T_IconMout_O_003_1_UI.T_IconMout_O_003_1_UI","QualityId":2}]},{"Id":850,"BreachId":21050046,"Level":1,"ConditionId":504003,"LevelLimit":40,"Consume":[{"Key":43020031,"Value":6},{"Key":41100032,"Value":6}],"GoldConsume":20000,"Items":[{"Key":43020031,"Value":6,"Icon":"/Game/Aki/UI/UIResources/Common/Image/IconWup/T_IconWup_005_UI.T_IconWup_005_UI","QualityId":2},{"Key":41100032,"Value":6,"Icon":"/Game/Aki/UI/UIResources/Common/Image/IconMout/T_IconMout_O_003_2_UI.T_IconMout_O_003_2_UI","QualityId":3}]},{"Id":851,"BreachId":21050046,"Level":2,"ConditionId":504004,"LevelLimit":50,"Consume":[{"Key":43020032,"Value":8},{"Key":41100033,"Value":4}],"GoldConsume":40000,"Items":[{"Key":43020032,"Value":8,"Icon":"/Game/Aki/UI/UIResources/Common/Image/IconWup/T_IconWup_006_UI.T_IconWup_006_UI","QualityId":3},{"Key":41100033,"Value":4,"Icon":"/Game/Aki/UI/UIResources/Common/Image/IconMout/T_IconMout_O_003_3_UI.T_IconMout_O_003_3_UI","QualityId":4}]},{"Id":852,"BreachId":21050046,"Level":3,"ConditionId":504005,"LevelLimit":60,"Consume":[{"Key":43020033,"Value":6},{"Key":41100033,"Value":6}],"GoldConsume":60000,"Items":[{"Key":43020033,"Value":6,"Icon":"/Game/Aki/UI/UIResources/Common/Image/IconWup/T_IconWup_007_UI.T_IconWup_007_UI","QualityId":4},{"Key":41100033,"Value":6,"Icon":"/Game/Aki/UI/UIResources/Common/Image/IconMout/T_IconMout_O_003_3_UI.T_IconMout_O_003_3_UI","QualityId":4}]},{"Id":853,"BreachId":21050046,"Level":4,"ConditionId":504006,"LevelLimit":70,"Consume":[{"Key":43020034,"Value":8},{"Key":41100034,"Value":4}],"GoldConsume":80000,"Items":[{"Key":43020034,"Value":8,"Icon":"/Game/Aki/UI/UIResources/Common/Image/IconWup/T_IconWup_008_UI.T_IconWup_008_UI","QualityId":5},{"Key":41100034,"Value":4,"Icon":"/Game/Aki/UI/UIResources/Common/Image/IconMout/T_IconMout_O_003_4_UI.T_IconMout_O_003_4_UI","QualityId":5}]},{"Id":854,"BreachId":21050046,"Level":5,"ConditionId":504007,"LevelLimit":80,"Consume":[{"Key":43020034,"Value":12},{"Key":41100034,"Value":8}],"GoldConsume":120000,"Items":[{"Key":43020034,"Value":12,"Icon":"/Game/Aki/UI/UIResources/Common/Image/IconWup/T_IconWup_008_UI.T_IconWup_008_UI","QualityId":5},{"Key":41100034,"Value":8,"Icon":"/Game/Aki/UI/UIResources/Common/Image/IconMout/T_IconMout_O_003_4_UI.T_IconMout_O_003_4_UI","QualityId":5}]},{"Id":855,"BreachId":21050046,"Level":6,"ConditionId":504007,"LevelLimit":90,"Consume":[],"GoldConsume":0,"Items":[]}],"Properties":[{"Name":"攻击","Icon":"/Game/Aki/UI/UIResources/Common/Image/IconAttribute/T_Iconpropertyredattack_UI.T_Iconpropertyredattack_UI","BaseValue":40,"GrowthValues":[{"Level":1,"Value":"40.00"},{"Level":2,"Value":"43.37"},{"Level":3,"Value":"46.74"},{"Level":4,"Value":"50.11"},{"Level":5,"Value":"53.48"},{"Level":6,"Value":"56.85"},{"Level":7,"Value":"60.22"},{"Level":8,"Value":"63.59"},{"Level":9,"Value":"66.96"},{"Level":10,"Value":"70.34"},{"Level":11,"Value":"73.70"},{"Level":12,"Value":"77.08"},{"Level":13,"Value":"80.45"},{"Level":14,"Value":"83.82"},{"Level":15,"Value":"87.19"},{"Level":16,"Value":"90.56"},{"Level":17,"Value":"93.93"},{"Level":18,"Value":"97.30"},{"Level":19,"Value":"100.67"},{"Level":20,"Value":"104.04"},{"Level":20.5,"Value":"130.71"},{"Level":21,"Value":"134.08"},{"Level":22,"Value":"137.45"},{"Level":23,"Value":"140.82"},{"Level":24,"Value":"144.19"},{"Level":25,"Value":"147.56"},{"Level":26,"Value":"150.94"},{"Level":27,"Value":"154.30"},{"Level":28,"Value":"157.68"},{"Level":29,"Value":"161.05"},{"Level":30,"Value":"164.42"},{"Level":31,"Value":"167.79"},{"Level":32,"Value":"171.16"},{"Level":33,"Value":"174.53"},{"Level":34,"Value":"177.90"},{"Level":35,"Value":"181.27"},{"Level":36,"Value":"184.64"},{"Level":37,"Value":"188.01"},{"Level":38,"Value":"191.38"},{"Level":39,"Value":"194.76"},{"Level":40,"Value":"198.12"},{"Level":40.5,"Value":"224.79"},{"Level":41,"Value":"228.16"},{"Level":42,"Value":"231.53"},{"Level":43,"Value":"234.90"},{"Level":44,"Value":"238.28"},{"Level":45,"Value":"241.64"},{"Level":46,"Value":"245.02"},{"Level":47,"Value":"248.39"},{"Level":48,"Value":"251.76"},{"Level":49,"Value":"255.13"},{"Level":50,"Value":"258.50"},{"Level":50.5,"Value":"285.17"},{"Level":51,"Value":"288.54"},{"Level":52,"Value":"291.91"},{"Level":53,"Value":"295.28"},{"Level":54,"Value":"298.65"},{"Level":55,"Value":"302.02"},{"Level":56,"Value":"305.39"},{"Level":57,"Value":"308.76"},{"Level":58,"Value":"312.13"},{"Level":59,"Value":"315.50"},{"Level":60,"Value":"318.88"},{"Level":60.5,"Value":"345.54"},{"Level":61,"Value":"348.91"},{"Level":62,"Value":"352.28"},{"Level":63,"Value":"355.65"},{"Level":64,"Value":"359.02"},{"Level":65,"Value":"362.40"},{"Level":66,"Value":"365.76"},{"Level":67,"Value":"369.14"},{"Level":68,"Value":"372.51"},{"Level":69,"Value":"375.88"},{"Level":70,"Value":"379.25"},{"Level":70.5,"Value":"405.92"},{"Level":71,"Value":"409.29"},{"Level":72,"Value":"412.66"},{"Level":73,"Value":"416.03"},{"Level":74,"Value":"419.40"},{"Level":75,"Value":"422.77"},{"Level":76,"Value":"426.14"},{"Level":77,"Value":"429.51"},{"Level":78,"Value":"432.88"},{"Level":79,"Value":"436.25"},{"Level":80,"Value":"439.62"},{"Level":80.5,"Value":"466.29"},{"Level":81,"Value":"469.66"},{"Level":82,"Value":"473.03"},{"Level":83,"Value":"476.40"},{"Level":84,"Value":"479.77"},{"Level":85,"Value":"483.14"},{"Level":86,"Value":"486.52"},{"Level":87,"Value":"489.88"},{"Level":88,"Value":"493.26"},{"Level":89,"Value":"496.63"},{"Level":90,"Value":"500.00"}]},{"Name":"暴击","Icon":"/Game/Aki/UI/UIResources/Common/Image/IconAttribute/T_Iconpropertyredbaoji_UI.T_Iconpropertyredbaoji_UI","BaseValue":800,"GrowthValues":[{"Level":1,"Value":"8.00%"},{"Level":2,"Value":"8.00%"},{"Level":3,"Value":"8.00%"},{"Level":4,"Value":"8.00%"},{"Level":5,"Value":"9.56%"},{"Level":6,"Value":"9.56%"},{"Level":7,"Value":"9.56%"},{"Level":8,"Value":"9.56%"},{"Level":9,"Value":"9.56%"},{"Level":10,"Value":"11.11%"},{"Level":11,"Value":"11.11%"},{"Level":12,"Value":"11.11%"},{"Level":13,"Value":"11.11%"},{"Level":14,"Value":"11.11%"},{"Level":15,"Value":"12.67%"},{"Level":16,"Value":"12.67%"},{"Level":17,"Value":"12.67%"},{"Level":18,"Value":"12.67%"},{"Level":19,"Value":"12.67%"},{"Level":20,"Value":"14.22%"},{"Level":20.5,"Value":"14.22%"},{"Level":21,"Value":"14.22%"},{"Level":22,"Value":"14.22%"},{"Level":23,"Value":"14.22%"},{"Level":24,"Value":"14.22%"},{"Level":25,"Value":"15.78%"},{"Level":26,"Value":"15.78%"},{"Level":27,"Value":"15.78%"},{"Level":28,"Value":"15.78%"},{"Level":29,"Value":"15.78%"},{"Level":30,"Value":"17.33%"},{"Level":31,"Value":"17.33%"},{"Level":32,"Value":"17.33%"},{"Level":33,"Value":"17.33%"},{"Level":34,"Value":"17.33%"},{"Level":35,"Value":"18.89%"},{"Level":36,"Value":"18.89%"},{"Level":37,"Value":"18.89%"},{"Level":38,"Value":"18.89%"},{"Level":39,"Value":"18.89%"},{"Level":40,"Value":"20.44%"},{"Level":40.5,"Value":"20.44%"},{"Level":41,"Value":"20.44%"},{"Level":42,"Value":"20.44%"},{"Level":43,"Value":"20.44%"},{"Level":44,"Value":"20.44%"},{"Level":45,"Value":"22.00%"},{"Level":46,"Value":"22.00%"},{"Level":47,"Value":"22.00%"},{"Level":48,"Value":"22.00%"},{"Level":49,"Value":"22.00%"},{"Level":50,"Value":"23.56%"},{"Level":50.5,"Value":"23.56%"},{"Level":51,"Value":"23.56%"},{"Level":52,"Value":"23.56%"},{"Level":53,"Value":"23.56%"},{"Level":54,"Value":"23.56%"},{"Level":55,"Value":"25.11%"},{"Level":56,"Value":"25.11%"},{"Level":57,"Value":"25.11%"},{"Level":58,"Value":"25.11%"},{"Level":59,"Value":"25.11%"},{"Level":60,"Value":"26.67%"},{"Level":60.5,"Value":"26.67%"},{"Level":61,"Value":"26.67%"},{"Level":62,"Value":"26.67%"},{"Level":63,"Value":"26.67%"},{"Level":64,"Value":"26.67%"},{"Level":65,"Value":"28.22%"},{"Level":66,"Value":"28.22%"},{"Level":67,"Value":"28.22%"},{"Level":68,"Value":"28.22%"},{"Level":69,"Value":"28.22%"},{"Level":70,"Value":"29.78%"},{"Level":70.5,"Value":"29.78%"},{"Level":71,"Value":"29.78%"},{"Level":72,"Value":"29.78%"},{"Level":73,"Value":"29.78%"},{"Level":74,"Value":"29.78%"},{"Level":75,"Value":"31.33%"},{"Level":76,"Value":"31.33%"},{"Level":77,"Value":"31.33%"},{"Level":78,"Value":"31.33%"},{"Level":79,"Value":"31.33%"},{"Level":80,"Value":"32.89%"},{"Level":80.5,"Value":"32.89%"},{"Level":81,"Value":"32.89%"},{"Level":82,"Value":"32.89%"},{"Level":83,"Value":"32.89%"},{"Level":84,"Value":"32.89%"},{"Level":85,"Value":"34.44%"},{"Level":86,"Value":"34.44%"},{"Level":87,"Value":"34.44%"},{"Level":88,"Value":"34.44%"},{"Level":89,"Value":"34.44%"},{"Level":90,"Value":"36.00%"}]}]}